Metadata-Version: 1.0
Name: statsdist
Version: 1.2
Summary: A simple custom package for working with Statistical distributions. 
Home-page: UNKNOWN
Author: Oluwadewalade Ade-Onojobi
Author-email: adewalade@gmail.com
License: UNKNOWN
Platform: UNKNOWN
